LICENSE
README.md
setup.py
messenger_python/__init__.py
messenger_python.egg-info/PKG-INFO
messenger_python.egg-info/SOURCES.txt
messenger_python.egg-info/dependency_links.txt
messenger_python.egg-info/top_level.txt